pyplt/__init__.py
pyplt/autoencoder.py
pyplt/exceptions.py
pyplt/experiment.py
pyplt/experimentmanager.py
pyplt/main_gui.py
pyplt/evaluation/__init__.py
pyplt/evaluation/base.py
pyplt/evaluation/cross_validation.py
pyplt/evaluation/holdout.py
pyplt/fsmethods/__init__.py
pyplt/fsmethods/base.py
pyplt/fsmethods/sfs.py
pyplt/fsmethods/wrappers.py
pyplt/gui/__init__.py
pyplt/gui/beginnermenu.py
pyplt/gui/mainmenu.py
pyplt/gui/experiment/__init__.py
pyplt/gui/experiment/progresswindow.py
pyplt/gui/experiment/singleexperimentwindow.py
pyplt/gui/experiment/dataset/__init__.py
pyplt/gui/experiment/dataset/loading.py
pyplt/gui/experiment/dataset/params.py
pyplt/gui/experiment/dataset/preview.py
pyplt/gui/experiment/featureselection/__init__.py
pyplt/gui/experiment/featureselection/featselectiontab.py
pyplt/gui/experiment/preflearning/__init__.py
pyplt/gui/experiment/preflearning/backprop_menu.py
pyplt/gui/experiment/preflearning/evaluator_menus.py
pyplt/gui/experiment/preflearning/pltab.py
pyplt/gui/experiment/preflearning/ranknet_menu.py
pyplt/gui/experiment/preflearning/ranksvm_menu.py
pyplt/gui/experiment/preprocessing/__init__.py
pyplt/gui/experiment/preprocessing/data_compression.py
pyplt/gui/experiment/preprocessing/preproctab.py
pyplt/gui/experiment/results/__init__.py
pyplt/gui/experiment/results/resultsscreen.py
pyplt/gui/util/__init__.py
pyplt/gui/util/colours.py
pyplt/gui/util/help.py
pyplt/gui/util/styles.py
pyplt/gui/util/supported_methods.py
pyplt/gui/util/tab_locking.py
pyplt/gui/util/text.py
pyplt/gui/util/windowstacking.py
pyplt/plalgorithms/__init__.py
pyplt/plalgorithms/backprop_tf.py
pyplt/plalgorithms/base.py
pyplt/plalgorithms/ranknet.py
pyplt/plalgorithms/ranksvc.py
pyplt/plalgorithms/ranksvm.py
pyplt/util/__init__.py
pyplt/util/enums.py
pyplt-0.2.3.dist-info/LICENSE.txt
pyplt-0.2.3.dist-info/METADATA
pyplt-0.2.3.dist-info/WHEEL
pyplt-0.2.3.dist-info/top_level.txt
pyplt-0.2.3.dist-info/RECORD
