Metadata-Version: 2.1
Name: pyplt
Version: 0.2.3
Summary: A toolbox for preference learning implemented in Python.
Home-page: https://github.com/institutedigitalgames/PLT
Author: Institute of Digital Games, University of Malta
Author-email: plt.digitalgames@um.edu.mt
License: UNKNOWN
Platform: UNKNOWN
Classifier: License :: OSI Approved :: GNU General Public License v3 (GPLv3)
Classifier: Programming Language :: Python :: 3
Classifier: Programming Language :: Python :: 3.6
Classifier: Operating System :: Microsoft :: Windows :: Windows 10
Classifier: Operating System :: POSIX :: Linux
Requires-Dist: keras (==2.2.4)
Requires-Dist: ttkthemes (==2.1.0)
Requires-Dist: numpy (==1.14.2)
Requires-Dist: matplotlib (==2.2.2)
Requires-Dist: pandas (==0.22.0)
Requires-Dist: tensorflow (==1.7.0)
Requires-Dist: scikit-learn (==0.19.1)
Requires-Dist: scipy (==1.0.1)
